fttb/__main__.py
fttb/utils.py
fttb/cmds/alias.py
fttb/cmds/clear.py
fttb/cmds/config.py
fttb/cmds/download.py
fttb/cmds/infos.py
fttb/cmds/list.py
fttb/cmds/remove.py
fttb/cmds/update.py
fttb/cmds/use.py
fttb-1.3.0.dist-info/METADATA
fttb-1.3.0.dist-info/WHEEL
fttb-1.3.0.dist-info/entry_points.txt
fttb-1.3.0.dist-info/top_level.txt
fttb-1.3.0.dist-info/RECORD
